{"content":{"type":"API","structure":"","server_on_load":"async ({\n  template,\n  params,\n  render,\n  db,\n  req,\n  reply,\n  user,\n  log,\n  ext,\n  isDev,\n}: Server) => {\n  // console.log(req.body);\n  const auser = req.body;\n  const loggedUser = await db.users.findFirst({\n    where: {\n      user_email: auser.user_email,\n      user_password: auser.user_password,\n    },\n  });\n\n  reply.send({\n    res: loggedUser,\n  })\n}","figma":{}},"title":"login","type":"cms-template","lang":"","status":"SYSTEM","parent_id":"54643","slug":"/api/login","site":"*","id":"22643"}